# Comparing `tmp/DataVisual-1.4.0-py3-none-any.whl.zip` & `tmp/DataVisual-1.4.1-py3-none-any.whl.zip`

## zipinfo {}

```diff
@@ -1,24 +1,23 @@
-Zip file size: 26866 bytes, number of entries: 22
--rw-r--r--  2.0 unx        6 b- defN 24-Mar-08 05:52 DataVisual/VERSION
--rw-r--r--  2.0 unx       78 b- defN 24-Mar-08 05:52 DataVisual/__init__.py
--rw-r--r--  2.0 unx     9772 b- defN 24-Mar-08 05:52 DataVisual/multi_array.py
--rw-r--r--  2.0 unx      862 b- defN 24-Mar-08 05:52 DataVisual/tables.py
--rw-r--r--  2.0 unx       52 b- defN 24-Mar-08 05:52 DataVisual/utils.py
--rw-r--r--  2.0 unx      310 b- defN 24-Mar-08 05:52 DataVisual/__pycache__/__init__.cpython-311.pyc
--rw-r--r--  2.0 unx    14150 b- defN 24-Mar-08 05:52 DataVisual/__pycache__/multi_array.cpython-311.pyc
--rw-r--r--  2.0 unx     1902 b- defN 24-Mar-08 05:52 DataVisual/__pycache__/tables.cpython-311.pyc
--rw-r--r--  2.0 unx       19 b- defN 24-Mar-08 05:52 DataVisual/examples/README.rst
--rw-r--r--  2.0 unx        0 b- defN 24-Mar-08 05:52 DataVisual/tools/__init__.py
--rw-r--r--  2.0 unx      903 b- defN 24-Mar-08 05:52 DataVisual/tools/directories.py
--rw-r--r--  2.0 unx       51 b- defN 24-Mar-08 05:52 DataVisual/units/__init__.py
--rw-r--r--  2.0 unx     9470 b- defN 24-Mar-08 05:52 DataVisual/units/base_class.py
--rw-r--r--  2.0 unx     3460 b- defN 24-Mar-08 05:52 DataVisual/units/components.py
--rw-r--r--  2.0 unx      244 b- defN 24-Mar-08 05:52 DataVisual/units/__pycache__/__init__.cpython-311.pyc
--rw-r--r--  2.0 unx    11371 b- defN 24-Mar-08 05:52 DataVisual/units/__pycache__/base_class.cpython-311.pyc
--rw-r--r--  2.0 unx     7629 b- defN 24-Mar-08 05:52 DataVisual/units/__pycache__/components.cpython-311.pyc
--rw-r--r--  2.0 unx     1073 b- defN 24-Mar-08 05:52 DataVisual-1.4.0.dist-info/LICENSE
--rw-r--r--  2.0 unx     3680 b- defN 24-Mar-08 05:52 DataVisual-1.4.0.dist-info/METADATA
--rw-r--r--  2.0 unx       92 b- defN 24-Mar-08 05:52 DataVisual-1.4.0.dist-info/WHEEL
--rw-r--r--  2.0 unx       11 b- defN 24-Mar-08 05:52 DataVisual-1.4.0.dist-info/top_level.txt
--rw-rw-r--  2.0 unx     1940 b- defN 24-Mar-08 05:52 DataVisual-1.4.0.dist-info/RECORD
-22 files, 67075 bytes uncompressed, 23652 bytes compressed:  64.7%
+Zip file size: 26769 bytes, number of entries: 21
+-rw-r--r--  2.0 unx        6 b- defN 24-May-29 18:41 DataVisual/VERSION
+-rw-r--r--  2.0 unx      187 b- defN 24-May-29 18:41 DataVisual/__init__.py
+-rw-r--r--  2.0 unx     9689 b- defN 24-May-29 18:41 DataVisual/multi_array.py
+-rw-r--r--  2.0 unx      844 b- defN 24-May-29 18:41 DataVisual/tables.py
+-rw-r--r--  2.0 unx      312 b- defN 24-May-29 18:42 DataVisual/__pycache__/__init__.cpython-311.pyc
+-rw-r--r--  2.0 unx    14123 b- defN 24-May-29 18:42 DataVisual/__pycache__/multi_array.cpython-311.pyc
+-rw-r--r--  2.0 unx     1866 b- defN 24-May-29 18:42 DataVisual/__pycache__/tables.cpython-311.pyc
+-rw-r--r--  2.0 unx       19 b- defN 24-May-29 18:41 DataVisual/examples/README.rst
+-rw-r--r--  2.0 unx        0 b- defN 24-May-29 18:41 DataVisual/tools/__init__.py
+-rw-r--r--  2.0 unx      903 b- defN 24-May-29 18:41 DataVisual/tools/directories.py
+-rw-r--r--  2.0 unx      143 b- defN 24-May-29 18:41 DataVisual/units/__init__.py
+-rw-r--r--  2.0 unx     9489 b- defN 24-May-29 18:41 DataVisual/units/base_class.py
+-rw-r--r--  2.0 unx     3460 b- defN 24-May-29 18:41 DataVisual/units/components.py
+-rw-r--r--  2.0 unx      246 b- defN 24-May-29 18:42 DataVisual/units/__pycache__/__init__.cpython-311.pyc
+-rw-r--r--  2.0 unx    11444 b- defN 24-May-29 18:42 DataVisual/units/__pycache__/base_class.cpython-311.pyc
+-rw-r--r--  2.0 unx     7629 b- defN 24-May-29 18:42 DataVisual/units/__pycache__/components.cpython-311.pyc
+-rw-r--r--  2.0 unx     1073 b- defN 24-May-29 18:42 DataVisual-1.4.1.dist-info/LICENSE
+-rw-r--r--  2.0 unx     3680 b- defN 24-May-29 18:42 DataVisual-1.4.1.dist-info/METADATA
+-rw-r--r--  2.0 unx       92 b- defN 24-May-29 18:42 DataVisual-1.4.1.dist-info/WHEEL
+-rw-r--r--  2.0 unx       11 b- defN 24-May-29 18:42 DataVisual-1.4.1.dist-info/top_level.txt
+-rw-rw-r--  2.0 unx     1868 b- defN 24-May-29 18:42 DataVisual-1.4.1.dist-info/RECORD
+21 files, 67084 bytes uncompressed, 23669 bytes compressed:  64.7%
```

## zipnote {}

```diff
@@ -6,17 +6,14 @@
 
 Filename: DataVisual/multi_array.py
 Comment: 
 
 Filename: DataVisual/tables.py
 Comment: 
 
-Filename: DataVisual/utils.py
-Comment: 
-
 Filename: DataVisual/__pycache__/__init__.cpython-311.pyc
 Comment: 
 
 Filename: DataVisual/__pycache__/multi_array.cpython-311.pyc
 Comment: 
 
 Filename: DataVisual/__pycache__/tables.cpython-311.pyc
@@ -45,23 +42,23 @@
 
 Filename: DataVisual/units/__pycache__/base_class.cpython-311.pyc
 Comment: 
 
 Filename: DataVisual/units/__pycache__/components.cpython-311.pyc
 Comment: 
 
-Filename: DataVisual-1.4.0.dist-info/LICENSE
+Filename: DataVisual-1.4.1.dist-info/LICENSE
 Comment: 
 
-Filename: DataVisual-1.4.0.dist-info/METADATA
+Filename: DataVisual-1.4.1.dist-info/METADATA
 Comment: 
 
-Filename: DataVisual-1.4.0.dist-info/WHEEL
+Filename: DataVisual-1.4.1.dist-info/WHEEL
 Comment: 
 
-Filename: DataVisual-1.4.0.dist-info/top_level.txt
+Filename: DataVisual-1.4.1.dist-info/top_level.txt
 Comment: 
 
-Filename: DataVisual-1.4.0.dist-info/RECORD
+Filename: DataVisual-1.4.1.dist-info/RECORD
 Comment: 
 
 Zip file comment:
```

## DataVisual/VERSION

```diff
@@ -1 +1 @@
-1.4.0
+1.4.1
```

## DataVisual/__init__.py

```diff
@@ -1,4 +1,8 @@
+#!/usr/bin/env python
+# -*- coding: utf-8 -*-
 
-from .multi_array import Array
-from .tables import Table
-from .units import *
+from .multi_array import Array  # noqa: F403 F401
+from .tables import Table  # noqa: F403 F401
+from .units import *  # noqa: F403 F401
+
+# -
```

## DataVisual/multi_array.py

```diff
@@ -315,19 +315,15 @@
 
             y_mean = numpy.mean(
                 self.y.values,
                 axis=std.position,
                 keepdims=True
             )
 
-            y_std = y_std[slicer]
-            y_mean = y_mean[slicer]
-            x_data = x.values
-
             ax.add_std_line(
-                x=x_data,
-                y_mean=y_mean.squeeze(),
-                y_std=y_std.squeeze(),
+                x=x.values,
+                y_mean=y_mean[slicer].squeeze(),
+                y_std=y_std[slicer].squeeze(),
                 label=label
             )
 
 # -
```

## DataVisual/tables.py

```diff
@@ -22,8 +22,8 @@
             parameter.position = idx
 
     def __getitem__(self, index: Union[int, slice]) -> Union[BaseUnit, List[BaseUnit]]:
         """Allows indexing directly into the parameters list."""
         return self.parameters[index]
 
     def __repr__(self) -> str:
-        return f"Xtable(size={len(self.parameters)})"
+        return str(self.parameters)
```

## DataVisual/__pycache__/__init__.cpython-311.pyc

### Python bytecode

```diff
@@ -1,35 +1,35 @@
 magic:    0xa70d0d0a
-moddate:  0x9ca7ea65 (Fri Mar  8 05:52:28 2024 UTC)
-files sz: 78
+moddate:  0xf7765766 (Wed May 29 18:41:59 2024 UTC)
+files sz: 187
 code
    argcount  : 0
    nlocals   : 0
    stacksize : 2
    flags     : 0
    code
       0x9700640064016c006d015a010100640064026c026d035a030100640064
       036c04540064045300
      0           0 RESUME                   0
    
-     2           2 LOAD_CONST               0 (1)
+     4           2 LOAD_CONST               0 (1)
                  4 LOAD_CONST               1 (('Array',))
                  6 IMPORT_NAME              0 (multi_array)
                  8 IMPORT_FROM              1 (Array)
                 10 STORE_NAME               1 (Array)
                 12 POP_TOP
    
-     3          14 LOAD_CONST               0 (1)
+     5          14 LOAD_CONST               0 (1)
                 16 LOAD_CONST               2 (('Table',))
                 18 IMPORT_NAME              2 (tables)
                 20 IMPORT_FROM              3 (Table)
                 22 STORE_NAME               3 (Table)
                 24 POP_TOP
    
-     4          26 LOAD_CONST               0 (1)
+     6          26 LOAD_CONST               0 (1)
                 28 LOAD_CONST               3 (('*',))
                 30 IMPORT_NAME              4 (units)
                 32 IMPORT_STAR
                 34 LOAD_CONST               4 (None)
                 36 RETURN_VALUE
    consts
       1
@@ -40,8 +40,8 @@
    names      ('multi_array', 'Array', 'tables', 'Table', 'units')
    varnames   ()
    freevars   ()
    cellvars   ()
    filename   '/home/runner/work/DataVisual/DataVisual/DataVisual/__init__.py'
    name       '<module>'
    firstlineno 1
-   lnotab 0x00ff02020c010c01
+   lnotab 0x00ff02040c010c01
```

## DataVisual/__pycache__/multi_array.cpython-311.pyc

### Python bytecode

```diff
@@ -1,10 +1,10 @@
 magic:    0xa70d0d0a
-moddate:  0x9ca7ea65 (Fri Mar  8 05:52:28 2024 UTC)
-files sz: 9772
+moddate:  0xf7765766 (Wed May 29 18:41:59 2024 UTC)
+files sz: 9689
 code
    argcount  : 0
    nlocals   : 0
    stacksize : 5
    flags     : 0
    code
       0x9700640064016c005a00640064026c016d025a020100640064036c036d
@@ -1243,25 +1243,25 @@
                name       'add_line_plot_to_ax'
                firstlineno 237
                lnotab
                   0x040d08013aff12044e020802280250022c021e0148010e021001020102
                   01020102fc040502fb08f4
             code
                argcount  : 5
-               nlocals   : 13
+               nlocals   : 12
                stacksize : 7
                flags     : 3
                code
                   0x870287049700640189045f000000000000000000880488026602640284
                   087403000000000000000000007c006a0200000000000000006a03000000
                   00000000006a040000000000000000a6010000ab01000000000000000044
                   00a6000000ab0000000000000000007d05740b000000000000000000006a
                   0600000000000000007c006a0200000000000000006a0300000000000000
                   0067007c05670264036701ac04a6030000ab0300000000000000005c0200
-                  007d067d077c07440090015d8c7d06740f000000000000000000007c076a
+                  007d067d077c07440090015d867d06740f000000000000000000007c076a
                   080000000000000000a6010000ab0100000000000000007d0889026a0900
                   0000000000000089046a0900000000000000006b000000000072517c08a0
                   0a000000000000000000000000000000000000000089026a090000000000
                   0000007417000000000000000000006405a6010000ab0100000000000000
                   00a6020000ab02000000000000000001007c08a00a000000000000000000
                   000000000000000000000089046a09000000000000000074170000000000
                   00000000006405a6010000ab010000000000000000a6020000ab02000000
@@ -1274,20 +1274,20 @@
                   000000000000000000000000007c08a6010000ab0100000000000000007d
                   09741b000000000000000000007c08a6010000ab0100000000000000007d
                   08740b000000000000000000006a0e00000000000000007c006a02000000
                   00000000006a03000000000000000089046a0900000000000000006401ac
                   06a6030000ab0300000000000000007d0a740b000000000000000000006a
                   0f00000000000000007c006a0200000000000000006a0300000000000000
                   0089046a0900000000000000006401ac06a6030000ab0300000000000000
-                  007d0b7c0a7c08190000000000000000007d0a7c0b7c0819000000000000
-                  0000007d0b89026a0300000000000000007d0c7c01a01000000000000000
-                  000000000000000000000000007c0c7c0ba0110000000000000000000000
-                  000000000000000000a6000000ab0000000000000000007c0aa011000000
-                  0000000000000000000000000000000000a6000000ab0000000000000000
-                  007c09ac07a6040000ab040000000000000000010090018c8e64055300
+                  007d0b7c01a010000000000000000000000000000000000000000089026a
+                  0300000000000000007c0b7c0819000000000000000000a0110000000000
+                  000000000000000000000000000000a6000000ab0000000000000000007c
+                  0a7c0819000000000000000000a011000000000000000000000000000000
+                  0000000000a6000000ab0000000000000000007c09ac07a6040000ab0400
+                  00000000000000010090018c8864055300
                              0 MAKE_CELL                2 (x)
                              2 MAKE_CELL                4 (std)
                
                276           4 RESUME                   0
                
                289           6 LOAD_CONST               1 (True)
                              8 LOAD_DEREF               4 (std)
@@ -1328,15 +1328,15 @@
                            176 UNPACK_SEQUENCE          2
                            180 STORE_FAST               6 (_)
                            182 STORE_FAST               7 (index)
                
                296         184 LOAD_FAST                7 (index)
                            186 GET_ITER
                        >>  188 EXTENDED_ARG             1
-                           190 FOR_ITER               396 (to 984)
+                           190 FOR_ITER               390 (to 972)
                            192 STORE_FAST               6 (_)
                
                297         194 LOAD_GLOBAL             15 (NULL + list)
                            206 LOAD_FAST                7 (index)
                            208 LOAD_ATTR                8 (multi_index)
                            218 PRECALL                  1
                            222 CALL                     1
@@ -1441,54 +1441,45 @@
                319         792 LOAD_CONST               1 (True)
                
                316         794 KW_NAMES                 6
                            796 PRECALL                  3
                            800 CALL                     3
                            810 STORE_FAST              11 (y_mean)
                
-               322         812 LOAD_FAST               10 (y_std)
-                           814 LOAD_FAST                8 (slicer)
-                           816 BINARY_SUBSCR
-                           826 STORE_FAST              10 (y_std)
-               
-               323         828 LOAD_FAST               11 (y_mean)
-                           830 LOAD_FAST                8 (slicer)
-                           832 BINARY_SUBSCR
-                           842 STORE_FAST              11 (y_mean)
-               
-               324         844 LOAD_DEREF               2 (x)
-                           846 LOAD_ATTR                3 (values)
-                           856 STORE_FAST              12 (x_data)
-               
-               326         858 LOAD_FAST                1 (ax)
-                           860 LOAD_METHOD             16 (add_std_line)
-               
-               327         882 LOAD_FAST               12 (x_data)
-               
-               328         884 LOAD_FAST               11 (y_mean)
-                           886 LOAD_METHOD             17 (squeeze)
-                           908 PRECALL                  0
-                           912 CALL                     0
-               
-               329         922 LOAD_FAST               10 (y_std)
-                           924 LOAD_METHOD             17 (squeeze)
-                           946 PRECALL                  0
-                           950 CALL                     0
-               
-               330         960 LOAD_FAST                9 (label)
-               
-               326         962 KW_NAMES                 7
-                           964 PRECALL                  4
-                           968 CALL                     4
-                           978 POP_TOP
-                           980 EXTENDED_ARG             1
-                           982 JUMP_BACKWARD          398 (to 188)
+               322         812 LOAD_FAST                1 (ax)
+                           814 LOAD_METHOD             16 (add_std_line)
+               
+               323         836 LOAD_DEREF               2 (x)
+                           838 LOAD_ATTR                3 (values)
+               
+               324         848 LOAD_FAST               11 (y_mean)
+                           850 LOAD_FAST                8 (slicer)
+                           852 BINARY_SUBSCR
+                           862 LOAD_METHOD             17 (squeeze)
+                           884 PRECALL                  0
+                           888 CALL                     0
+               
+               325         898 LOAD_FAST               10 (y_std)
+                           900 LOAD_FAST                8 (slicer)
+                           902 BINARY_SUBSCR
+                           912 LOAD_METHOD             17 (squeeze)
+                           934 PRECALL                  0
+                           938 CALL                     0
+               
+               326         948 LOAD_FAST                9 (label)
+               
+               322         950 KW_NAMES                 7
+                           952 PRECALL                  4
+                           956 CALL                     4
+                           966 POP_TOP
+                           968 EXTENDED_ARG             1
+                           970 JUMP_BACKWARD          392 (to 188)
                
-               296     >>  984 LOAD_CONST               5 (None)
-                           986 RETURN_VALUE
+               296     >>  972 LOAD_CONST               5 (None)
+                           974 RETURN_VALUE
                consts
                   '\n        Method plot the multi-dimensional array with the x key as abscissa.\n        kwargs can be passed as standard input to the artist STDLine from MPSPLots.\n\n        :param      x:    Key of the self dict which represent the abscissa.\n        :type       x:    BaseUnit\n        :param      y:    Key of the self dict which represent the ordinate.\n        :type       y:    BaseUnit\n\n        :returns:   No returns\n        :rtype:     None\n        '
                   True
                   code
                      argcount  : 1
                      nlocals   : 3
                      stacksize : 5
@@ -1529,24 +1520,24 @@
                      lnotab 0x0a01
                   'multi_index'
                   ('flags',)
                   None
                   ('axis', 'keepdims')
                   ('x', 'y_mean', 'y_std', 'label')
                names      ('is_base', 'enumerate', 'y', 'values', 'shape', 'numpy', 'nested_iters', 'list', 'multi_index', 'position', 'insert', 'slice', 'get_diff_label', 'tuple', 'std', 'mean', 'add_std_line', 'squeeze')
-               varnames   ('self', 'ax', 'x', 'y', 'std', 'dimensions', '_', 'index', 'slicer', 'label', 'y_std', 'y_mean', 'x_data')
+               varnames   ('self', 'ax', 'x', 'y', 'std', 'dimensions', '_', 'index', 'slicer', 'label', 'y_std', 'y_mean')
                freevars   ()
                cellvars   ('x', 'std')
                filename   '/home/runner/work/DataVisual/DataVisual/DataVisual/multi_array.py'
                name       'add_std_line_to_ax'
                firstlineno 276
                lnotab
                   0x060d0e010a013aff12044e020a012802200150015202500150022a021e
-                  02160116010c0102fd1206160116010c0102fd1206100110010e02180102
-                  012601260102fc16e2
+                  02160116010c0102fd1206160116010c0102fd120618010c013201320102
+                  fc16e6
             (False, None, False)
          names      ('__name__', '__module__', '__qualname__', '__doc__', 'Table', '__annotations__', 'Any', 'scale', 'str', '__post_init__', '_validate_attributes', 'property', 'tuple', 'shape', 'Callable', 'generate_y_copy', 'mean', 'std', 'rsd', 'numpy', 'ndarray', '_normalize', 'BaseUnit', 'bool', 'SceneList', 'plot', 'Axis', 'list', 'add_box_info_to_ax', 'get_diff_label', 'add_line_plot_to_ax', 'add_std_line_to_ax')
          varnames   ()
          freevars   ()
          cellvars   ()
          filename   '/home/runner/work/DataVisual/DataVisual/DataVisual/multi_array.py'
          name       'Array'
```

## DataVisual/__pycache__/tables.cpython-311.pyc

### Python bytecode

```diff
@@ -1,10 +1,10 @@
 magic:    0xa70d0d0a
-moddate:  0x9ca7ea65 (Fri Mar  8 05:52:28 2024 UTC)
-files sz: 862
+moddate:  0xf7765766 (Wed May 29 18:41:59 2024 UTC)
+files sz: 844
 code
    argcount  : 0
    nlocals   : 0
    stacksize : 5
    flags     : 0
    code
       0x9700640064016c006d015a010100640064026c026d035a036d045a0401
@@ -185,36 +185,30 @@
                filename   '/home/runner/work/DataVisual/DataVisual/DataVisual/tables.py'
                name       '__getitem__'
                firstlineno 24
                lnotab 0x0202
             code
                argcount  : 1
                nlocals   : 1
-               stacksize : 4
+               stacksize : 3
                flags     : 3
                code
-                  0x970064017401000000000000000000007c006a010000000000000000a6
-                  010000ab0100000000000000009b0064029d035300
+                  0x97007401000000000000000000007c006a010000000000000000a60100
+                  00ab0100000000000000005300
                 28           0 RESUME                   0
                
-                29           2 LOAD_CONST               1 ('Xtable(size=')
-                             4 LOAD_GLOBAL              1 (NULL + len)
-                            16 LOAD_FAST                0 (self)
-                            18 LOAD_ATTR                1 (parameters)
-                            28 PRECALL                  1
-                            32 CALL                     1
-                            42 FORMAT_VALUE             0
-                            44 LOAD_CONST               2 (')')
-                            46 BUILD_STRING             3
-                            48 RETURN_VALUE
+                29           2 LOAD_GLOBAL              1 (NULL + str)
+                            14 LOAD_FAST                0 (self)
+                            16 LOAD_ATTR                1 (parameters)
+                            26 PRECALL                  1
+                            30 CALL                     1
+                            40 RETURN_VALUE
                consts
                   None
-                  'Xtable(size='
-                  ')'
-               names      ('len', 'parameters')
+               names      ('str', 'parameters')
                varnames   ('self',)
                freevars   ()
                cellvars   ()
                filename   '/home/runner/work/DataVisual/DataVisual/DataVisual/tables.py'
                name       '__repr__'
                firstlineno 28
                lnotab 0x0201
```

## DataVisual/units/__init__.py

```diff
@@ -1,2 +1,8 @@
-from .components import *
-from .base_class import *
+#!/usr/bin/env python
+# -*- coding: utf-8 -*-
+
+from .components import *  # noqa: F403 F401
+from .base_class import *  # noqa: F403 F401
+
+
+# -
```

## DataVisual/units/base_class.py

```diff
@@ -98,15 +98,15 @@
     def scale_values(self) -> None:
         if not self.use_prefix:
             self.long_prefix = ''
             self.short_prefix = ''
             self.values = self.base_values
             return
 
-        if self.base_values is None or self.value_representation is not None:
+        if None in self.base_values or self.value_representation is not None:
             self.long_prefix = ''
             self.short_prefix = ''
             return
 
         if self.normalized:
             self.long_prefix = ''
             self.short_prefix = ''
@@ -120,15 +120,16 @@
         self.long_prefix = long_prefix
 
         self.short_prefix = short_prefix
 
         self.values = self.base_values * (multiplier ** -self.power)
 
     def set_base_values(self, base_values: numpy.ndarray) -> numpy.ndarray:
-        self.base_values = base_values
+        self.base_values = numpy.atleast_1d(base_values)
+
         self.scale_values()
 
     def __repr__(self) -> str:
         """Returns a string representation of the BaseUnit instance."""
         unit_representation = self.get_unit()
 
         if unit_representation == '':
```

## DataVisual/units/__pycache__/__init__.cpython-311.pyc

### Python bytecode

```diff
@@ -1,24 +1,24 @@
 magic:    0xa70d0d0a
-moddate:  0x9ca7ea65 (Fri Mar  8 05:52:28 2024 UTC)
-files sz: 51
+moddate:  0xf7765766 (Wed May 29 18:41:59 2024 UTC)
+files sz: 143
 code
    argcount  : 0
    nlocals   : 0
    stacksize : 2
    flags     : 0
    code 0x9700640064016c005400640064016c01540064025300
      0           0 RESUME                   0
    
-     1           2 LOAD_CONST               0 (1)
+     4           2 LOAD_CONST               0 (1)
                  4 LOAD_CONST               1 (('*',))
                  6 IMPORT_NAME              0 (components)
                  8 IMPORT_STAR
    
-     2          10 LOAD_CONST               0 (1)
+     5          10 LOAD_CONST               0 (1)
                 12 LOAD_CONST               1 (('*',))
                 14 IMPORT_NAME              1 (base_class)
                 16 IMPORT_STAR
                 18 LOAD_CONST               2 (None)
                 20 RETURN_VALUE
    consts
       1
@@ -27,8 +27,8 @@
    names      ('components', 'base_class')
    varnames   ()
    freevars   ()
    cellvars   ()
    filename   '/home/runner/work/DataVisual/DataVisual/DataVisual/units/__init__.py'
    name       '<module>'
    firstlineno 1
-   lnotab 0x00ff02010801
+   lnotab 0x00ff02040801
```

## DataVisual/units/__pycache__/base_class.cpython-311.pyc

### Python bytecode

```diff
@@ -1,10 +1,10 @@
 magic:    0xa70d0d0a
-moddate:  0x9ca7ea65 (Fri Mar  8 05:52:28 2024 UTC)
-files sz: 9470
+moddate:  0xf7765766 (Wed May 29 18:41:59 2024 UTC)
+files sz: 9489
 code
    argcount  : 0
    nlocals   : 0
    stacksize : 5
    flags     : 0
    code
       0x9700640064016c005a00640064026c016d025a02010002004700640384
@@ -286,140 +286,140 @@
                      138 LOAD_NAME                5 (numpy)
                      140 LOAD_ATTR                6 (ndarray)
                      150 BUILD_TUPLE              4
                      152 LOAD_CONST              18 (<code object set_base_values, file "/home/runner/work/DataVisual/DataVisual/DataVisual/units/base_class.py", line 126>)
                      154 MAKE_FUNCTION            4 (annotations)
                      156 STORE_NAME              10 (set_base_values)
          
-         130         158 LOAD_CONST              16 ('return')
+         131         158 LOAD_CONST              16 ('return')
                      160 LOAD_NAME                4 (str)
                      162 BUILD_TUPLE              2
-                     164 LOAD_CONST              19 (<code object __repr__, file "/home/runner/work/DataVisual/DataVisual/DataVisual/units/base_class.py", line 130>)
+                     164 LOAD_CONST              19 (<code object __repr__, file "/home/runner/work/DataVisual/DataVisual/DataVisual/units/base_class.py", line 131>)
                      166 MAKE_FUNCTION            4 (annotations)
                      168 STORE_NAME              11 (__repr__)
          
-         139         170 LOAD_CONST              16 ('return')
+         140         170 LOAD_CONST              16 ('return')
                      172 LOAD_NAME                4 (str)
                      174 BUILD_TUPLE              2
-                     176 LOAD_CONST              20 (<code object get_unit, file "/home/runner/work/DataVisual/DataVisual/DataVisual/units/base_class.py", line 139>)
+                     176 LOAD_CONST              20 (<code object get_unit, file "/home/runner/work/DataVisual/DataVisual/DataVisual/units/base_class.py", line 140>)
                      178 MAKE_FUNCTION            4 (annotations)
                      180 STORE_NAME              12 (get_unit)
          
-         143         182 LOAD_NAME               13 (property)
+         144         182 LOAD_NAME               13 (property)
          
-         144         184 LOAD_CONST              16 ('return')
+         145         184 LOAD_CONST              16 ('return')
                      186 LOAD_NAME               14 (int)
                      188 BUILD_TUPLE              2
-                     190 LOAD_CONST              21 (<code object size, file "/home/runner/work/DataVisual/DataVisual/DataVisual/units/base_class.py", line 143>)
+                     190 LOAD_CONST              21 (<code object size, file "/home/runner/work/DataVisual/DataVisual/DataVisual/units/base_class.py", line 144>)
                      192 MAKE_FUNCTION            4 (annotations)
          
-         143         194 PRECALL                  0
+         144         194 PRECALL                  0
                      198 CALL                     0
          
-         144         208 STORE_NAME              15 (size)
+         145         208 STORE_NAME              15 (size)
          
-         148         210 LOAD_NAME               13 (property)
+         149         210 LOAD_NAME               13 (property)
          
-         149         212 LOAD_CONST              16 ('return')
+         150         212 LOAD_CONST              16 ('return')
                      214 LOAD_NAME               16 (tuple)
                      216 BUILD_TUPLE              2
-                     218 LOAD_CONST              22 (<code object shape, file "/home/runner/work/DataVisual/DataVisual/DataVisual/units/base_class.py", line 148>)
+                     218 LOAD_CONST              22 (<code object shape, file "/home/runner/work/DataVisual/DataVisual/DataVisual/units/base_class.py", line 149>)
                      220 MAKE_FUNCTION            4 (annotations)
          
-         148         222 PRECALL                  0
+         149         222 PRECALL                  0
                      226 CALL                     0
          
-         149         236 STORE_NAME              17 (shape)
+         150         236 STORE_NAME              17 (shape)
          
-         153         238 LOAD_NAME               18 (staticmethod)
+         154         238 LOAD_NAME               18 (staticmethod)
          
-         154         240 LOAD_CONST              23 ('order_of_magnitude')
+         155         240 LOAD_CONST              23 ('order_of_magnitude')
                      242 LOAD_NAME               19 (float)
                      244 LOAD_CONST              16 ('return')
                      246 LOAD_NAME                4 (str)
                      248 BUILD_TUPLE              4
-                     250 LOAD_CONST              24 (<code object closest_prefix_order, file "/home/runner/work/DataVisual/DataVisual/DataVisual/units/base_class.py", line 153>)
+                     250 LOAD_CONST              24 (<code object closest_prefix_order, file "/home/runner/work/DataVisual/DataVisual/DataVisual/units/base_class.py", line 154>)
                      252 MAKE_FUNCTION            4 (annotations)
          
-         153         254 PRECALL                  0
+         154         254 PRECALL                  0
                      258 CALL                     0
          
-         154         268 STORE_NAME              20 (closest_prefix_order)
+         155         268 STORE_NAME              20 (closest_prefix_order)
          
-         183         270 LOAD_CONST              16 ('return')
+         184         270 LOAD_CONST              16 ('return')
                      272 LOAD_NAME               16 (tuple)
                      274 LOAD_NAME                4 (str)
                      276 LOAD_NAME                4 (str)
                      278 BUILD_TUPLE              2
                      280 BINARY_SUBSCR
                      290 BUILD_TUPLE              2
-                     292 LOAD_CONST              25 (<code object get_closest_prefix_string, file "/home/runner/work/DataVisual/DataVisual/DataVisual/units/base_class.py", line 183>)
+                     292 LOAD_CONST              25 (<code object get_closest_prefix_string, file "/home/runner/work/DataVisual/DataVisual/DataVisual/units/base_class.py", line 184>)
                      294 MAKE_FUNCTION            4 (annotations)
                      296 STORE_NAME              21 (get_closest_prefix_string)
          
-         201         298 NOP
+         202         298 NOP
          
-         202         300 NOP
+         203         300 NOP
          
-         203         302 NOP
+         204         302 NOP
          
-         204         304 NOP
+         205         304 NOP
          
-         199         306 LOAD_CONST              35 ((None, False, False, True))
+         200         306 LOAD_CONST              35 ((None, False, False, True))
                      308 LOAD_CONST              26 ('index')
          
-         201         310 LOAD_NAME               14 (int)
+         202         310 LOAD_NAME               14 (int)
          
-         199         312 LOAD_CONST              27 ('add_unit')
+         200         312 LOAD_CONST              27 ('add_unit')
          
-         202         314 LOAD_NAME                7 (bool)
+         203         314 LOAD_NAME                7 (bool)
          
-         199         316 LOAD_CONST              28 ('use_short_repr')
+         200         316 LOAD_CONST              28 ('use_short_repr')
          
-         203         318 LOAD_NAME                7 (bool)
+         204         318 LOAD_NAME                7 (bool)
          
-         199         320 LOAD_CONST              11 ('use_prefix')
+         200         320 LOAD_CONST              11 ('use_prefix')
          
-         204         322 LOAD_NAME                7 (bool)
+         205         322 LOAD_NAME                7 (bool)
          
-         199         324 LOAD_CONST              16 ('return')
+         200         324 LOAD_CONST              16 ('return')
          
-         204         326 LOAD_NAME                4 (str)
+         205         326 LOAD_NAME                4 (str)
          
-         199         328 BUILD_TUPLE             10
-                     330 LOAD_CONST              29 (<code object get_representation, file "/home/runner/work/DataVisual/DataVisual/DataVisual/units/base_class.py", line 199>)
+         200         328 BUILD_TUPLE             10
+                     330 LOAD_CONST              29 (<code object get_representation, file "/home/runner/work/DataVisual/DataVisual/DataVisual/units/base_class.py", line 200>)
                      332 MAKE_FUNCTION            5 (defaults, annotations)
                      334 STORE_NAME              22 (get_representation)
          
-         232         336 LOAD_CONST              28 ('use_short_repr')
+         233         336 LOAD_CONST              28 ('use_short_repr')
                      338 LOAD_NAME                7 (bool)
                      340 LOAD_CONST              16 ('return')
                      342 LOAD_NAME                4 (str)
                      344 BUILD_TUPLE              4
-                     346 LOAD_CONST              30 (<code object _choose_label, file "/home/runner/work/DataVisual/DataVisual/DataVisual/units/base_class.py", line 232>)
+                     346 LOAD_CONST              30 (<code object _choose_label, file "/home/runner/work/DataVisual/DataVisual/DataVisual/units/base_class.py", line 233>)
                      348 MAKE_FUNCTION            4 (annotations)
                      350 STORE_NAME              23 (_choose_label)
          
-         237         352 LOAD_CONST              26 ('index')
+         238         352 LOAD_CONST              26 ('index')
                      354 LOAD_NAME               14 (int)
                      356 LOAD_CONST              11 ('use_prefix')
                      358 LOAD_NAME                7 (bool)
                      360 BUILD_TUPLE              4
-                     362 LOAD_CONST              31 (<code object _get_value_with_prefix, file "/home/runner/work/DataVisual/DataVisual/DataVisual/units/base_class.py", line 237>)
+                     362 LOAD_CONST              31 (<code object _get_value_with_prefix, file "/home/runner/work/DataVisual/DataVisual/DataVisual/units/base_class.py", line 238>)
                      364 MAKE_FUNCTION            4 (annotations)
                      366 STORE_NAME              24 (_get_value_with_prefix)
          
-         245         368 LOAD_CONST              27 ('add_unit')
+         246         368 LOAD_CONST              27 ('add_unit')
                      370 LOAD_NAME                7 (bool)
                      372 LOAD_CONST              11 ('use_prefix')
                      374 LOAD_NAME                7 (bool)
                      376 LOAD_CONST              16 ('return')
                      378 LOAD_NAME                4 (str)
                      380 BUILD_TUPLE              6
-                     382 LOAD_CONST              32 (<code object _get_unit_string, file "/home/runner/work/DataVisual/DataVisual/DataVisual/units/base_class.py", line 245>)
+                     382 LOAD_CONST              32 (<code object _get_unit_string, file "/home/runner/work/DataVisual/DataVisual/DataVisual/units/base_class.py", line 246>)
                      384 MAKE_FUNCTION            4 (annotations)
                      386 STORE_NAME              25 (_get_unit_string)
                      388 LOAD_CONST               2 (None)
                      390 RETURN_VALUE
          consts
             'BaseUnit'
             "\n    A base class for representing measurement units with features for normalization,\n    SI prefix adjustment, and formatted string representation.\n\n    Attributes:\n        long_label (str): Descriptive name of the unit.\n        short_label (str): Abbreviated label of the unit.\n        string_format (str): Python format specifier for converting numerical values to strings.\n        values (float | np.ndarray): The numerical values associated with this unit.\n        use_long_label_for_repr (bool): Flag indicating whether the long label should be used in the __repr__ output.\n        use_prefix (bool): Determines whether SI prefixes are automatically used when representing values.\n        value_representation (float | np.ndarray): Custom representation of the values, if any.\n\n    Methods:\n        __repr__: Returns a string representation of the unit instance.\n        get_unit: Returns the unit string, considering normalization.\n        size: Returns the number of values.\n        shape: Returns the shape of the values array.\n        values: Property that returns the measurement values, normalized if applicable.\n        get_closest_prefix_string: Identifies the closest SI prefix based on the values' magnitude.\n        get_representation: Generates a formatted string representation for the unit and its values.\n    "
@@ -544,26 +544,27 @@
                argcount  : 1
                nlocals   : 4
                stacksize : 3
                flags     : 3
                code
                   0x97007c006a000000000000000000731c64017c005f0100000000000000
                   0064017c005f0200000000000000007c006a0300000000000000007c005f
-                  040000000000000000640053007c006a03000000000000000081077c006a
-                  050000000000000000811064017c005f01000000000000000064017c005f
-                  020000000000000000640053007c006a060000000000000000723664017c
-                  005f01000000000000000064017c005f0200000000000000007c006a0300
-                  000000000000007c006a030000000000000000a007000000000000000000
-                  0000000000000000000000a6000000ab0000000000000000007a0b00007c
-                  005f040000000000000000640053007c00a0080000000000000000000000
-                  000000000000000000a6000000ab0000000000000000005c0200007d017d
-                  027412000000000000000000006a0a00000000000000007c011900000000
-                  00000000007d037c017c005f0100000000000000007c027c005f02000000
-                  00000000007c006a0300000000000000007c037c006a0b00000000000000
-                  000b007a0800007a0500007c005f04000000000000000064005300
+                  0400000000000000006400530064007c006a030000000000000000760073
+                  077c006a050000000000000000811064017c005f01000000000000000064
+                  017c005f020000000000000000640053007c006a06000000000000000072
+                  3664017c005f01000000000000000064017c005f0200000000000000007c
+                  006a0300000000000000007c006a030000000000000000a0070000000000
+                  000000000000000000000000000000a6000000ab0000000000000000007a
+                  0b00007c005f040000000000000000640053007c00a00800000000000000
+                  00000000000000000000000000a6000000ab0000000000000000005c0200
+                  007d017d027412000000000000000000006a0a00000000000000007c0119
+                  0000000000000000007d037c017c005f0100000000000000007c027c005f
+                  0200000000000000007c006a0300000000000000007c037c006a0b000000
+                  00000000000b007a0800007a0500007c005f040000000000000000640053
+                  00
                 98           0 RESUME                   0
                
                 99           2 LOAD_FAST                0 (self)
                              4 LOAD_ATTR                0 (use_prefix)
                             14 POP_JUMP_FORWARD_IF_TRUE    28 (to 72)
                
                100          16 LOAD_CONST               1 ('')
@@ -578,166 +579,173 @@
                             46 LOAD_ATTR                3 (base_values)
                             56 LOAD_FAST                0 (self)
                             58 STORE_ATTR               4 (values)
                
                103          68 LOAD_CONST               0 (None)
                             70 RETURN_VALUE
                
-               105     >>   72 LOAD_FAST                0 (self)
-                            74 LOAD_ATTR                3 (base_values)
-                            84 POP_JUMP_FORWARD_IF_NONE     7 (to 100)
-                            86 LOAD_FAST                0 (self)
-                            88 LOAD_ATTR                5 (value_representation)
-                            98 POP_JUMP_FORWARD_IF_NONE    16 (to 132)
-               
-               106     >>  100 LOAD_CONST               1 ('')
-                           102 LOAD_FAST                0 (self)
-                           104 STORE_ATTR               1 (long_prefix)
-               
-               107         114 LOAD_CONST               1 ('')
-                           116 LOAD_FAST                0 (self)
-                           118 STORE_ATTR               2 (short_prefix)
-               
-               108         128 LOAD_CONST               0 (None)
-                           130 RETURN_VALUE
-               
-               110     >>  132 LOAD_FAST                0 (self)
-                           134 LOAD_ATTR                6 (normalized)
-                           144 POP_JUMP_FORWARD_IF_FALSE    54 (to 254)
-               
-               111         146 LOAD_CONST               1 ('')
-                           148 LOAD_FAST                0 (self)
-                           150 STORE_ATTR               1 (long_prefix)
-               
-               112         160 LOAD_CONST               1 ('')
-                           162 LOAD_FAST                0 (self)
-                           164 STORE_ATTR               2 (short_prefix)
-               
-               113         174 LOAD_FAST                0 (self)
-                           176 LOAD_ATTR                3 (base_values)
-                           186 LOAD_FAST                0 (self)
-                           188 LOAD_ATTR                3 (base_values)
-                           198 LOAD_METHOD              7 (max)
-                           220 PRECALL                  0
-                           224 CALL                     0
-                           234 BINARY_OP               11 (/)
-                           238 LOAD_FAST                0 (self)
-                           240 STORE_ATTR               4 (values)
-               
-               114         250 LOAD_CONST               0 (None)
-                           252 RETURN_VALUE
-               
-               116     >>  254 LOAD_FAST                0 (self)
-                           256 LOAD_METHOD              8 (get_closest_prefix_string)
-                           278 PRECALL                  0
-                           282 CALL                     0
-                           292 UNPACK_SEQUENCE          2
-                           296 STORE_FAST               1 (long_prefix)
-                           298 STORE_FAST               2 (short_prefix)
-               
-               118         300 LOAD_GLOBAL             18 (UnitMeta)
-                           312 LOAD_ATTR               10 (prefixes)
-                           322 LOAD_FAST                1 (long_prefix)
-                           324 BINARY_SUBSCR
-                           334 STORE_FAST               3 (multiplier)
-               
-               120         336 LOAD_FAST                1 (long_prefix)
-                           338 LOAD_FAST                0 (self)
-                           340 STORE_ATTR               1 (long_prefix)
-               
-               122         350 LOAD_FAST                2 (short_prefix)
-                           352 LOAD_FAST                0 (self)
-                           354 STORE_ATTR               2 (short_prefix)
-               
-               124         364 LOAD_FAST                0 (self)
-                           366 LOAD_ATTR                3 (base_values)
-                           376 LOAD_FAST                3 (multiplier)
-                           378 LOAD_FAST                0 (self)
-                           380 LOAD_ATTR               11 (power)
-                           390 UNARY_NEGATIVE
-                           392 BINARY_OP                8 (**)
-                           396 BINARY_OP                5 (*)
-                           400 LOAD_FAST                0 (self)
-                           402 STORE_ATTR               4 (values)
-                           412 LOAD_CONST               0 (None)
-                           414 RETURN_VALUE
+               105     >>   72 LOAD_CONST               0 (None)
+                            74 LOAD_FAST                0 (self)
+                            76 LOAD_ATTR                3 (base_values)
+                            86 CONTAINS_OP              0
+                            88 POP_JUMP_FORWARD_IF_TRUE     7 (to 104)
+                            90 LOAD_FAST                0 (self)
+                            92 LOAD_ATTR                5 (value_representation)
+                           102 POP_JUMP_FORWARD_IF_NONE    16 (to 136)
+               
+               106     >>  104 LOAD_CONST               1 ('')
+                           106 LOAD_FAST                0 (self)
+                           108 STORE_ATTR               1 (long_prefix)
+               
+               107         118 LOAD_CONST               1 ('')
+                           120 LOAD_FAST                0 (self)
+                           122 STORE_ATTR               2 (short_prefix)
+               
+               108         132 LOAD_CONST               0 (None)
+                           134 RETURN_VALUE
+               
+               110     >>  136 LOAD_FAST                0 (self)
+                           138 LOAD_ATTR                6 (normalized)
+                           148 POP_JUMP_FORWARD_IF_FALSE    54 (to 258)
+               
+               111         150 LOAD_CONST               1 ('')
+                           152 LOAD_FAST                0 (self)
+                           154 STORE_ATTR               1 (long_prefix)
+               
+               112         164 LOAD_CONST               1 ('')
+                           166 LOAD_FAST                0 (self)
+                           168 STORE_ATTR               2 (short_prefix)
+               
+               113         178 LOAD_FAST                0 (self)
+                           180 LOAD_ATTR                3 (base_values)
+                           190 LOAD_FAST                0 (self)
+                           192 LOAD_ATTR                3 (base_values)
+                           202 LOAD_METHOD              7 (max)
+                           224 PRECALL                  0
+                           228 CALL                     0
+                           238 BINARY_OP               11 (/)
+                           242 LOAD_FAST                0 (self)
+                           244 STORE_ATTR               4 (values)
+               
+               114         254 LOAD_CONST               0 (None)
+                           256 RETURN_VALUE
+               
+               116     >>  258 LOAD_FAST                0 (self)
+                           260 LOAD_METHOD              8 (get_closest_prefix_string)
+                           282 PRECALL                  0
+                           286 CALL                     0
+                           296 UNPACK_SEQUENCE          2
+                           300 STORE_FAST               1 (long_prefix)
+                           302 STORE_FAST               2 (short_prefix)
+               
+               118         304 LOAD_GLOBAL             18 (UnitMeta)
+                           316 LOAD_ATTR               10 (prefixes)
+                           326 LOAD_FAST                1 (long_prefix)
+                           328 BINARY_SUBSCR
+                           338 STORE_FAST               3 (multiplier)
+               
+               120         340 LOAD_FAST                1 (long_prefix)
+                           342 LOAD_FAST                0 (self)
+                           344 STORE_ATTR               1 (long_prefix)
+               
+               122         354 LOAD_FAST                2 (short_prefix)
+                           356 LOAD_FAST                0 (self)
+                           358 STORE_ATTR               2 (short_prefix)
+               
+               124         368 LOAD_FAST                0 (self)
+                           370 LOAD_ATTR                3 (base_values)
+                           380 LOAD_FAST                3 (multiplier)
+                           382 LOAD_FAST                0 (self)
+                           384 LOAD_ATTR               11 (power)
+                           394 UNARY_NEGATIVE
+                           396 BINARY_OP                8 (**)
+                           400 BINARY_OP                5 (*)
+                           404 LOAD_FAST                0 (self)
+                           406 STORE_ATTR               4 (values)
+                           416 LOAD_CONST               0 (None)
+                           418 RETURN_VALUE
                consts
                   None
                   ''
                names      ('use_prefix', 'long_prefix', 'short_prefix', 'base_values', 'values', 'value_representation', 'normalized', 'max', 'get_closest_prefix_string', 'UnitMeta', 'prefixes', 'power')
                varnames   ('self', 'long_prefix', 'short_prefix', 'multiplier')
                freevars   ()
                cellvars   ()
                filename   '/home/runner/work/DataVisual/DataVisual/DataVisual/units/base_class.py'
                name       'scale_values'
                firstlineno 98
                lnotab
-                  0x02010e010e010e01180104021c010e010e0104020e010e010e014c0104
+                  0x02010e010e010e011801040220010e010e0104020e010e010e014c0104
                   022e0224020e020e02
             code
                argcount  : 2
                nlocals   : 2
-               stacksize : 2
+               stacksize : 3
                flags     : 3
                code
-                  0x97007c017c005f0000000000000000007c00a001000000000000000000
-                  0000000000000000000000a6000000ab0000000000000000000100640053
-                  00
+                  0x97007401000000000000000000006a0100000000000000007c01a60100
+                  00ab0100000000000000007c005f0200000000000000007c00a003000000
+                  0000000000000000000000000000000000a6000000ab0000000000000000
+                  00010064005300
                126           0 RESUME                   0
                
-               127           2 LOAD_FAST                1 (base_values)
-                             4 LOAD_FAST                0 (self)
-                             6 STORE_ATTR               0 (base_values)
-               
-               128          16 LOAD_FAST                0 (self)
-                            18 LOAD_METHOD              1 (scale_values)
-                            40 PRECALL                  0
-                            44 CALL                     0
-                            54 POP_TOP
-                            56 LOAD_CONST               0 (None)
-                            58 RETURN_VALUE
+               127           2 LOAD_GLOBAL              1 (NULL + numpy)
+                            14 LOAD_ATTR                1 (atleast_1d)
+                            24 LOAD_FAST                1 (base_values)
+                            26 PRECALL                  1
+                            30 CALL                     1
+                            40 LOAD_FAST                0 (self)
+                            42 STORE_ATTR               2 (base_values)
+               
+               129          52 LOAD_FAST                0 (self)
+                            54 LOAD_METHOD              3 (scale_values)
+                            76 PRECALL                  0
+                            80 CALL                     0
+                            90 POP_TOP
+                            92 LOAD_CONST               0 (None)
+                            94 RETURN_VALUE
                consts
                   None
-               names      ('base_values', 'scale_values')
+               names      ('numpy', 'atleast_1d', 'base_values', 'scale_values')
                varnames   ('self', 'base_values')
                freevars   ()
                cellvars   ()
                filename   '/home/runner/work/DataVisual/DataVisual/DataVisual/units/base_class.py'
                name       'set_base_values'
                firstlineno 126
-               lnotab 0x02010e01
+               lnotab 0x02013202
             code
                argcount  : 1
                nlocals   : 2
                stacksize : 4
                flags     : 3
                code
                   0x97007c00a0000000000000000000000000000000000000000000a60000
                   00ab0000000000000000007d017c0164016b020000000072087c006a0100
                   000000000000009b0053007c006a0100000000000000009b0064027c019b
                   0064039d045300
-               130           0 RESUME                   0
+               131           0 RESUME                   0
                
-               132           2 LOAD_FAST                0 (self)
+               133           2 LOAD_FAST                0 (self)
                              4 LOAD_METHOD              0 (get_unit)
                             26 PRECALL                  0
                             30 CALL                     0
                             40 STORE_FAST               1 (unit_representation)
                
-               134          42 LOAD_FAST                1 (unit_representation)
+               135          42 LOAD_FAST                1 (unit_representation)
                             44 LOAD_CONST               1 ('')
                             46 COMPARE_OP               2 (==)
                             52 POP_JUMP_FORWARD_IF_FALSE     8 (to 70)
                
-               135          54 LOAD_FAST                0 (self)
+               136          54 LOAD_FAST                0 (self)
                             56 LOAD_ATTR                1 (long_label)
                             66 FORMAT_VALUE             0
                             68 RETURN_VALUE
                
-               137     >>   70 LOAD_FAST                0 (self)
+               138     >>   70 LOAD_FAST                0 (self)
                             72 LOAD_ATTR                1 (long_label)
                             82 FORMAT_VALUE             0
                             84 LOAD_CONST               2 (' [')
                             86 LOAD_FAST                1 (unit_representation)
                             88 FORMAT_VALUE             0
                             90 LOAD_CONST               3 (']')
                             92 BUILD_STRING             4
@@ -749,27 +757,27 @@
                   ']'
                names      ('get_unit', 'long_label')
                varnames   ('self', 'unit_representation')
                freevars   ()
                cellvars   ()
                filename   '/home/runner/work/DataVisual/DataVisual/DataVisual/units/base_class.py'
                name       '__repr__'
-               firstlineno 130
+               firstlineno 131
                lnotab 0x020228020c011002
             code
                argcount  : 1
                nlocals   : 1
                stacksize : 1
                flags     : 3
                code
                   0x97007c006a000000000000000000720264016e067c006a010000000000
                   0000005300
-               139           0 RESUME                   0
+               140           0 RESUME                   0
                
-               141           2 LOAD_FAST                0 (self)
+               142           2 LOAD_FAST                0 (self)
                              4 LOAD_ATTR                0 (normalized)
                             14 POP_JUMP_FORWARD_IF_FALSE     2 (to 20)
                             16 LOAD_CONST               1 ('A.U.')
                             18 JUMP_FORWARD             6 (to 32)
                        >>   20 LOAD_FAST                0 (self)
                             22 LOAD_ATTR                1 (unit)
                        >>   32 RETURN_VALUE
@@ -778,149 +786,149 @@
                   'A.U.'
                names      ('normalized', 'unit')
                varnames   ('self',)
                freevars   ()
                cellvars   ()
                filename   '/home/runner/work/DataVisual/DataVisual/DataVisual/units/base_class.py'
                name       'get_unit'
-               firstlineno 139
+               firstlineno 140
                lnotab 0x0202
             code
                argcount  : 1
                nlocals   : 1
                stacksize : 3
                flags     : 3
                code
                   0x97007401000000000000000000006a0100000000000000007c006a0200
                   00000000000000a6010000ab0100000000000000005300
-               143           0 RESUME                   0
+               144           0 RESUME                   0
                
-               146           2 LOAD_GLOBAL              1 (NULL + numpy)
+               147           2 LOAD_GLOBAL              1 (NULL + numpy)
                             14 LOAD_ATTR                1 (size)
                             24 LOAD_FAST                0 (self)
                             26 LOAD_ATTR                2 (base_values)
                             36 PRECALL                  1
                             40 CALL                     1
                             50 RETURN_VALUE
                consts
                   'Returns the number of values.'
                names      ('numpy', 'size', 'base_values')
                varnames   ('self',)
                freevars   ()
                cellvars   ()
                filename   '/home/runner/work/DataVisual/DataVisual/DataVisual/units/base_class.py'
                name       'size'
-               firstlineno 143
+               firstlineno 144
                lnotab 0x0203
             code
                argcount  : 1
                nlocals   : 1
                stacksize : 3
                flags     : 3
                code
                   0x97007401000000000000000000006a0100000000000000007c006a0200
                   00000000000000a6010000ab0100000000000000005300
-               148           0 RESUME                   0
+               149           0 RESUME                   0
                
-               151           2 LOAD_GLOBAL              1 (NULL + numpy)
+               152           2 LOAD_GLOBAL              1 (NULL + numpy)
                             14 LOAD_ATTR                1 (shape)
                             24 LOAD_FAST                0 (self)
                             26 LOAD_ATTR                2 (values)
                             36 PRECALL                  1
                             40 CALL                     1
                             50 RETURN_VALUE
                consts
                   'Returns the shape of the values.'
                names      ('numpy', 'shape', 'values')
                varnames   ('self',)
                freevars   ()
                cellvars   ()
                filename   '/home/runner/work/DataVisual/DataVisual/DataVisual/units/base_class.py'
                name       'shape'
-               firstlineno 148
+               firstlineno 149
                lnotab 0x0203
             'order_of_magnitude'
             code
                argcount  : 1
                nlocals   : 1
                stacksize : 2
                flags     : 3
                code
                   0x97007c0064016b00000000007202640253007c0064036b000000000072
                   02640253007c0064046b00000000007202640553007c0064066b00000000
                   007202640753007c0064086b01000000007202640953007c00640a6b0000
                   0000007202640b53007c00640c6b00000000007202640d53007c00640e6b
                   00000000007202640f530064105300
-               153           0 RESUME                   0
+               154           0 RESUME                   0
                
-               164           2 LOAD_FAST                0 (order_of_magnitude)
+               165           2 LOAD_FAST                0 (order_of_magnitude)
                              4 LOAD_CONST               1 (-9)
                              6 COMPARE_OP               0 (<)
                             12 POP_JUMP_FORWARD_IF_FALSE     2 (to 18)
                
-               165          14 LOAD_CONST               2 ('nano')
+               166          14 LOAD_CONST               2 ('nano')
                             16 RETURN_VALUE
                
-               166     >>   18 LOAD_FAST                0 (order_of_magnitude)
+               167     >>   18 LOAD_FAST                0 (order_of_magnitude)
                             20 LOAD_CONST               3 (-6)
                             22 COMPARE_OP               0 (<)
                             28 POP_JUMP_FORWARD_IF_FALSE     2 (to 34)
                
-               167          30 LOAD_CONST               2 ('nano')
+               168          30 LOAD_CONST               2 ('nano')
                             32 RETURN_VALUE
                
-               168     >>   34 LOAD_FAST                0 (order_of_magnitude)
+               169     >>   34 LOAD_FAST                0 (order_of_magnitude)
                             36 LOAD_CONST               4 (-3)
                             38 COMPARE_OP               0 (<)
                             44 POP_JUMP_FORWARD_IF_FALSE     2 (to 50)
                
-               169          46 LOAD_CONST               5 ('micro')
+               170          46 LOAD_CONST               5 ('micro')
                             48 RETURN_VALUE
                
-               170     >>   50 LOAD_FAST                0 (order_of_magnitude)
+               171     >>   50 LOAD_FAST                0 (order_of_magnitude)
                             52 LOAD_CONST               6 (0)
                             54 COMPARE_OP               0 (<)
                             60 POP_JUMP_FORWARD_IF_FALSE     2 (to 66)
                
-               171          62 LOAD_CONST               7 ('milli')
+               172          62 LOAD_CONST               7 ('milli')
                             64 RETURN_VALUE
                
-               172     >>   66 LOAD_FAST                0 (order_of_magnitude)
+               173     >>   66 LOAD_FAST                0 (order_of_magnitude)
                             68 LOAD_CONST               8 (3)
                             70 COMPARE_OP               1 (<=)
                             76 POP_JUMP_FORWARD_IF_FALSE     2 (to 82)
                
-               173          78 LOAD_CONST               9 ('base')
+               174          78 LOAD_CONST               9 ('base')
                             80 RETURN_VALUE
                
-               174     >>   82 LOAD_FAST                0 (order_of_magnitude)
+               175     >>   82 LOAD_FAST                0 (order_of_magnitude)
                             84 LOAD_CONST              10 (6)
                             86 COMPARE_OP               0 (<)
                             92 POP_JUMP_FORWARD_IF_FALSE     2 (to 98)
                
-               175          94 LOAD_CONST              11 ('kilo')
+               176          94 LOAD_CONST              11 ('kilo')
                             96 RETURN_VALUE
                
-               176     >>   98 LOAD_FAST                0 (order_of_magnitude)
+               177     >>   98 LOAD_FAST                0 (order_of_magnitude)
                            100 LOAD_CONST              12 (9)
                            102 COMPARE_OP               0 (<)
                            108 POP_JUMP_FORWARD_IF_FALSE     2 (to 114)
                
-               177         110 LOAD_CONST              13 ('mega')
+               178         110 LOAD_CONST              13 ('mega')
                            112 RETURN_VALUE
                
-               178     >>  114 LOAD_FAST                0 (order_of_magnitude)
+               179     >>  114 LOAD_FAST                0 (order_of_magnitude)
                            116 LOAD_CONST              14 (12)
                            118 COMPARE_OP               0 (<)
                            124 POP_JUMP_FORWARD_IF_FALSE     2 (to 130)
                
-               179         126 LOAD_CONST              15 ('giga')
+               180         126 LOAD_CONST              15 ('giga')
                            128 RETURN_VALUE
                
-               181     >>  130 LOAD_CONST              16 ('tera')
+               182     >>  130 LOAD_CONST              16 ('tera')
                            132 RETURN_VALUE
                consts
                   '\n        Determines the closest SI prefix based on the order of magnitude of the values.\n\n        Args:\n            order_of_magnitude (float): The order of magnitude of the values.\n\n        Returns:\n            str: The closest SI prefix.\n        '
                   -9
                   'nano'
                   -6
                   -3
@@ -938,15 +946,15 @@
                   'tera'
                names      ()
                varnames   ('order_of_magnitude',)
                freevars   ()
                cellvars   ()
                filename   '/home/runner/work/DataVisual/DataVisual/DataVisual/units/base_class.py'
                name       'closest_prefix_order'
-               firstlineno 153
+               firstlineno 154
                lnotab
                   0x020b0c0104010c0104010c0104010c0104010c0104010c0104010c0104
                   010c010402
             code
                argcount  : 1
                nlocals   : 4
                stacksize : 5
@@ -959,17 +967,17 @@
                   07000000000000000000006a050000000000000000740d00000000000000
                   0000007c01a6010000ab010000000000000000a6010000ab010000000000
                   0000007c006a0700000000000000007a0b00007d027c00a0080000000000
                   0000000000000000000000000000007c02a6010000ab0100000000000000
                   007d037c037412000000000000000000006a0a0000000000000000a00b00
                   000000000000000000000000000000000000007c036401a6020000ab0200
                   0000000000000066025300
-               183           0 RESUME                   0
+               184           0 RESUME                   0
                
-               190           2 LOAD_GLOBAL              1 (NULL + isinstance)
+               191           2 LOAD_GLOBAL              1 (NULL + isinstance)
                             14 LOAD_FAST                0 (self)
                             16 LOAD_ATTR                1 (base_values)
                             26 LOAD_GLOBAL              4 (Iterable)
                             38 PRECALL                  2
                             42 CALL                     2
                             52 POP_JUMP_FORWARD_IF_FALSE    25 (to 104)
                             54 LOAD_GLOBAL              7 (NULL + numpy)
@@ -979,35 +987,35 @@
                             88 PRECALL                  1
                             92 CALL                     1
                            102 JUMP_FORWARD             6 (to 116)
                        >>  104 LOAD_FAST                0 (self)
                            106 LOAD_ATTR                1 (base_values)
                        >>  116 STORE_FAST               1 (base_value)
                
-               192         118 LOAD_GLOBAL              7 (NULL + numpy)
+               193         118 LOAD_GLOBAL              7 (NULL + numpy)
                            130 LOAD_ATTR                5 (log10)
                            140 LOAD_GLOBAL             13 (NULL + abs)
                            152 LOAD_FAST                1 (base_value)
                            154 PRECALL                  1
                            158 CALL                     1
                            168 PRECALL                  1
                            172 CALL                     1
                            182 LOAD_FAST                0 (self)
                            184 LOAD_ATTR                7 (power)
                            194 BINARY_OP               11 (/)
                            198 STORE_FAST               2 (magnitude)
                
-               194         200 LOAD_FAST                0 (self)
+               195         200 LOAD_FAST                0 (self)
                            202 LOAD_METHOD              8 (closest_prefix_order)
                            224 LOAD_FAST                2 (magnitude)
                            226 PRECALL                  1
                            230 CALL                     1
                            240 STORE_FAST               3 (prefix)
                
-               197         242 LOAD_FAST                3 (prefix)
+               198         242 LOAD_FAST                3 (prefix)
                            244 LOAD_GLOBAL             18 (UnitMeta)
                            256 LOAD_ATTR               10 (prefix_to_string)
                            266 LOAD_METHOD             11 (get)
                            288 LOAD_FAST                3 (prefix)
                            290 LOAD_CONST               1 ('')
                            292 PRECALL                  2
                            296 CALL                     2
@@ -1018,15 +1026,15 @@
                   ''
                names      ('isinstance', 'base_values', 'Iterable', 'numpy', 'max', 'log10', 'abs', 'power', 'closest_prefix_order', 'UnitMeta', 'prefix_to_string', 'get')
                varnames   ('self', 'base_value', 'magnitude', 'prefix')
                freevars   ()
                cellvars   ()
                filename   '/home/runner/work/DataVisual/DataVisual/DataVisual/units/base_class.py'
                name       'get_closest_prefix_string'
-               firstlineno 183
+               firstlineno 184
                lnotab 0x0207740252022a03
             'index'
             'add_unit'
             'use_short_repr'
             code
                argcount  : 5
                nlocals   : 9
@@ -1036,111 +1044,111 @@
                   0x97007c00a00000000000000000000000000000000000000000007c03a6
                   010000ab0100000000000000007d057c00a0010000000000000000000000
                   0000000000000000007c017c04a6020000ab0200000000000000007d067c
                   00a00200000000000000000000000000000000000000007c027c04a60200
                   00ab0200000000000000007d077c059b007d087c06810f7c0864027c067c
                   006a0300000000000000009b009b049d027a0d00007d087c02720d7c0764
                   03760172097c0864047c079b0064059d037a0d00007d087c085300
-               199           0 RESUME                   0
+               200           0 RESUME                   0
                
-               218           2 LOAD_FAST                0 (self)
+               219           2 LOAD_FAST                0 (self)
                              4 LOAD_METHOD              0 (_choose_label)
                             26 LOAD_FAST                3 (use_short_repr)
                             28 PRECALL                  1
                             32 CALL                     1
                             42 STORE_FAST               5 (label)
                
-               219          44 LOAD_FAST                0 (self)
+               220          44 LOAD_FAST                0 (self)
                             46 LOAD_METHOD              1 (_get_value_with_prefix)
                             68 LOAD_FAST                1 (index)
                             70 LOAD_FAST                4 (use_prefix)
                             72 PRECALL                  2
                             76 CALL                     2
                             86 STORE_FAST               6 (value)
                
-               220          88 LOAD_FAST                0 (self)
+               221          88 LOAD_FAST                0 (self)
                             90 LOAD_METHOD              2 (_get_unit_string)
                            112 LOAD_FAST                2 (add_unit)
                            114 LOAD_FAST                4 (use_prefix)
                            116 PRECALL                  2
                            120 CALL                     2
                            130 STORE_FAST               7 (unit)
                
-               223         132 LOAD_FAST                5 (label)
+               224         132 LOAD_FAST                5 (label)
                            134 FORMAT_VALUE             0
                            136 STORE_FAST               8 (representation)
                
-               224         138 LOAD_FAST                6 (value)
+               225         138 LOAD_FAST                6 (value)
                            140 POP_JUMP_FORWARD_IF_NONE    15 (to 172)
                
-               225         142 LOAD_FAST                8 (representation)
+               226         142 LOAD_FAST                8 (representation)
                            144 LOAD_CONST               2 (': ')
                            146 LOAD_FAST                6 (value)
                            148 LOAD_FAST                0 (self)
                            150 LOAD_ATTR                3 (string_format)
                            160 FORMAT_VALUE             0
                            162 FORMAT_VALUE             4 (with format)
                            164 BUILD_STRING             2
                            166 BINARY_OP               13 (+=)
                            170 STORE_FAST               8 (representation)
                
-               227     >>  172 LOAD_FAST                2 (add_unit)
+               228     >>  172 LOAD_FAST                2 (add_unit)
                            174 POP_JUMP_FORWARD_IF_FALSE    13 (to 202)
                            176 LOAD_FAST                7 (unit)
                            178 LOAD_CONST               3 (('', 'base'))
                            180 CONTAINS_OP              1
                            182 POP_JUMP_FORWARD_IF_FALSE     9 (to 202)
                
-               228         184 LOAD_FAST                8 (representation)
+               229         184 LOAD_FAST                8 (representation)
                            186 LOAD_CONST               4 (' [')
                            188 LOAD_FAST                7 (unit)
                            190 FORMAT_VALUE             0
                            192 LOAD_CONST               5 (']')
                            194 BUILD_STRING             3
                            196 BINARY_OP               13 (+=)
                            200 STORE_FAST               8 (representation)
                
-               230     >>  202 LOAD_FAST                8 (representation)
+               231     >>  202 LOAD_FAST                8 (representation)
                            204 RETURN_VALUE
                consts
                   '\n        Generates a formatted string representation of the unit, optionally including its value,\n        label, and unit prefix.\n\n        Args:\n            index (int, optional): The index of the value to format. Relevant for array-like values.\n            add_unit (bool, optional): Flag to include the unit in the representation.\n            use_short_repr (bool, optional): Flag to use the short label instead of the long label.\n            use_prefix (bool, optional): Flag to use SI prefixes in the value representation.\n\n        Returns:\n            str: The formatted string representation of the unit.\n        '
                   None
                   ': '
                   ('', 'base')
                   ' ['
                   ']'
                names      ('_choose_label', '_get_value_with_prefix', '_get_unit_string', 'string_format')
                varnames   ('self', 'index', 'add_unit', 'use_short_repr', 'use_prefix', 'label', 'value', 'unit', 'representation')
                freevars   ()
                cellvars   ()
                filename   '/home/runner/work/DataVisual/DataVisual/DataVisual/units/base_class.py'
                name       'get_representation'
-               firstlineno 199
+               firstlineno 200
                lnotab 0x02132a012c012c03060104011e020c011202
             code
                argcount  : 2
                nlocals   : 3
                stacksize : 4
                flags     : 3
                code
                   0x97007c0172077c006a0000000000000000006e067c006a010000000000
                   0000007d027c02a002000000000000000000000000000000000000000064
                   016402a6020000ab0200000000000000005300
-               232           0 RESUME                   0
+               233           0 RESUME                   0
                
-               234           2 LOAD_FAST                1 (use_short_repr)
+               235           2 LOAD_FAST                1 (use_short_repr)
                              4 POP_JUMP_FORWARD_IF_FALSE     7 (to 20)
                              6 LOAD_FAST                0 (self)
                              8 LOAD_ATTR                0 (short_label)
                             18 JUMP_FORWARD             6 (to 32)
                        >>   20 LOAD_FAST                0 (self)
                             22 LOAD_ATTR                1 (long_label)
                        >>   32 STORE_FAST               2 (label)
                
-               235          34 LOAD_FAST                2 (label)
+               236          34 LOAD_FAST                2 (label)
                             36 LOAD_METHOD              2 (replace)
                             58 LOAD_CONST               1 ('_')
                             60 LOAD_CONST               2 (' ')
                             62 PRECALL                  2
                             66 CALL                     2
                             76 RETURN_VALUE
                consts
@@ -1149,104 +1157,104 @@
                   ' '
                names      ('short_label', 'long_label', 'replace')
                varnames   ('self', 'use_short_repr', 'label')
                freevars   ()
                cellvars   ()
                filename   '/home/runner/work/DataVisual/DataVisual/DataVisual/units/base_class.py'
                name       '_choose_label'
-               firstlineno 232
+               firstlineno 233
                lnotab 0x02022001
             code
                argcount  : 3
                nlocals   : 3
                stacksize : 2
                flags     : 3
                code
                   0x97007c006a00000000000000000081167c0180077c006a000000000000
                   0000006e0c7c006a0000000000000000007c011900000000000000000053
                   007c01810d7c006a0100000000000000007c011900000000000000000053
                   0064015300
-               237           0 RESUME                   0
+               238           0 RESUME                   0
                
-               239           2 LOAD_FAST                0 (self)
+               240           2 LOAD_FAST                0 (self)
                              4 LOAD_ATTR                0 (value_representation)
                             14 POP_JUMP_FORWARD_IF_NONE    22 (to 60)
                
-               240          16 LOAD_FAST                1 (index)
+               241          16 LOAD_FAST                1 (index)
                             18 POP_JUMP_FORWARD_IF_NOT_NONE     7 (to 34)
                             20 LOAD_FAST                0 (self)
                             22 LOAD_ATTR                0 (value_representation)
                             32 JUMP_FORWARD            12 (to 58)
                        >>   34 LOAD_FAST                0 (self)
                             36 LOAD_ATTR                0 (value_representation)
                             46 LOAD_FAST                1 (index)
                             48 BINARY_SUBSCR
                        >>   58 RETURN_VALUE
                
-               242     >>   60 LOAD_FAST                1 (index)
+               243     >>   60 LOAD_FAST                1 (index)
                             62 POP_JUMP_FORWARD_IF_NONE    13 (to 90)
                
-               243          64 LOAD_FAST                0 (self)
+               244          64 LOAD_FAST                0 (self)
                             66 LOAD_ATTR                1 (values)
                             76 LOAD_FAST                1 (index)
                             78 BINARY_SUBSCR
                             88 RETURN_VALUE
                
-               242     >>   90 LOAD_CONST               1 (None)
+               243     >>   90 LOAD_CONST               1 (None)
                             92 RETURN_VALUE
                consts
                   'Retrieves the value at the given index, considering SI prefix adjustments.'
                   None
                names      ('value_representation', 'values')
                varnames   ('self', 'index', 'use_prefix')
                freevars   ()
                cellvars   ()
                filename   '/home/runner/work/DataVisual/DataVisual/DataVisual/units/base_class.py'
                name       '_get_value_with_prefix'
-               firstlineno 237
+               firstlineno 238
                lnotab 0x02020e012c0204011aff
             code
                argcount  : 3
                nlocals   : 5
                stacksize : 2
                flags     : 3
                code
                   0x97007c017302640153007c006a00000000000000000072077c006a0100
                   000000000000006e0164017d037c006a02000000000000000064026b0200
                   000000720264016e067c006a0200000000000000007d047c049b007c039b
                   009d025300
-               245           0 RESUME                   0
+               246           0 RESUME                   0
                
-               251           2 LOAD_FAST                1 (add_unit)
+               252           2 LOAD_FAST                1 (add_unit)
                              4 POP_JUMP_FORWARD_IF_TRUE     2 (to 10)
                
-               252           6 LOAD_CONST               1 ('')
+               253           6 LOAD_CONST               1 ('')
                              8 RETURN_VALUE
                
-               254     >>   10 LOAD_FAST                0 (self)
+               255     >>   10 LOAD_FAST                0 (self)
                             12 LOAD_ATTR                0 (unit)
                             22 POP_JUMP_FORWARD_IF_FALSE     7 (to 38)
                             24 LOAD_FAST                0 (self)
                             26 LOAD_ATTR                1 (short_unit)
                             36 JUMP_FORWARD             1 (to 40)
                        >>   38 LOAD_CONST               1 ('')
                        >>   40 STORE_FAST               3 (unit)
                
-               256          42 LOAD_FAST                0 (self)
+               257          42 LOAD_FAST                0 (self)
                             44 LOAD_ATTR                2 (short_prefix)
                             54 LOAD_CONST               2 ('base')
                             56 COMPARE_OP               2 (==)
                             62 POP_JUMP_FORWARD_IF_FALSE     2 (to 68)
                             64 LOAD_CONST               1 ('')
                             66 JUMP_FORWARD             6 (to 80)
                        >>   68 LOAD_FAST                0 (self)
                             70 LOAD_ATTR                2 (short_prefix)
                        >>   80 STORE_FAST               4 (short_prefix)
                
-               258          82 LOAD_FAST                4 (short_prefix)
+               259          82 LOAD_FAST                4 (short_prefix)
                             84 FORMAT_VALUE             0
                             86 LOAD_FAST                3 (unit)
                             88 FORMAT_VALUE             0
                             90 BUILD_STRING             2
                             92 RETURN_VALUE
                consts
                   '\n        Constructs the unit string, including the appropriate SI prefix if required.\n\n        Returns an empty string if add_unit is False.\n        '
@@ -1254,30 +1262,30 @@
                   'base'
                names      ('unit', 'short_unit', 'short_prefix')
                varnames   ('self', 'add_unit', 'use_prefix', 'unit', 'short_prefix')
                freevars   ()
                cellvars   ()
                filename   '/home/runner/work/DataVisual/DataVisual/DataVisual/units/base_class.py'
                name       '_get_unit_string'
-               firstlineno 245
+               firstlineno 246
                lnotab 0x02060401040220022802
             (None, '', None, False, None, None, False, True)
             ('return', None)
             (None, False, False, True)
          names      ('__name__', '__module__', '__qualname__', '__doc__', 'str', 'numpy', 'ndarray', 'bool', '__init__', 'scale_values', 'set_base_values', '__repr__', 'get_unit', 'property', 'int', 'size', 'tuple', 'shape', 'staticmethod', 'float', 'closest_prefix_order', 'get_closest_prefix_string', 'get_representation', '_choose_label', '_get_value_with_prefix', '_get_unit_string')
          varnames   ()
          freevars   ()
          cellvars   ()
          filename   '/home/runner/work/DataVisual/DataVisual/DataVisual/units/base_class.py'
          name       'BaseUnit'
          firstlineno 49
          lnotab
             0x0a01041a020102010201020102010201020102f6040202fe020308fd02
             0402fc020512fb020602fa020702f9020812f8020902f7020a02f6081908
-            1c24040c090c0402010aff0e01020402010aff0e01020402010eff0e0102
+            1c24050c090c0402010aff0e01020402010aff0e01020402010eff0e0102
             1d1c1202010201020102fb040202fe020302fd020402fc020502fb020502
             fb082110051008
       'BaseUnit'
    names      ('numpy', 'typing', 'Iterable', 'type', 'UnitMeta', 'BaseUnit')
    varnames   ()
    freevars   ()
    cellvars   ()
```

## DataVisual/units/__pycache__/components.cpython-311.pyc

### Python bytecode

```diff
@@ -1,9 +1,9 @@
 magic:    0xa70d0d0a
-moddate:  0x9ca7ea65 (Fri Mar  8 05:52:28 2024 UTC)
+moddate:  0xf7765766 (Wed May 29 18:41:59 2024 UTC)
 files sz: 3460
 code
    argcount  : 0
    nlocals   : 0
    stacksize : 6
    flags     : 0
    code
```

## Comparing `DataVisual-1.4.0.dist-info/LICENSE` & `DataVisual-1.4.1.dist-info/LICENSE`

 * *Files identical despite different names*

## Comparing `DataVisual-1.4.0.dist-info/METADATA` & `DataVisual-1.4.1.dist-info/METADATA`

 * *Files 0% similar despite different names*

```diff
@@ -1,10 +1,10 @@
 Metadata-Version: 2.1
 Name: DataVisual
-Version: 1.4.0
+Version: 1.4.1
 Summary: A package multidimensional data visualisation.
 Home-page: https://github.com/MartinPdeS/DataVisual
 Author: Martin Poinsinet de Sivry
 Author-email: Martin.poinsinet.de.sivry@gmail.com
 License: MIT
 Platform: unix
 Platform: linux
```

## Comparing `DataVisual-1.4.0.dist-info/RECORD` & `DataVisual-1.4.1.dist-info/RECORD`

 * *Files 20% similar despite different names*

```diff
@@ -1,22 +1,21 @@
-DataVisual/VERSION,sha256=eLWRQAxWt7Z7jLOyuKjmXpCTiX8Czgh45rVAXGhiD6c,6
-DataVisual/__init__.py,sha256=1fC9snWS5Ytzrh1bYlinrb6RnAtpQ9KA-SdOAXaCl_Q,78
-DataVisual/multi_array.py,sha256=_igwLi35pKIId_gMPllfkX_hVMofggPeVFJS6NZ69UU,9772
-DataVisual/tables.py,sha256=DkypG81eixu16SkcS2CoKAc0JybCOHtIVnHENrKQ9J4,862
-DataVisual/utils.py,sha256=kTCGYrnx4DDHA6dfeMTPeHXV8I7KRsCyPrWSv86qi0M,52
-DataVisual/__pycache__/__init__.cpython-311.pyc,sha256=d6oXvWOmSz2_7g5t0nCQZ2Qny3fFc_cYxujgVb3sMZw,310
-DataVisual/__pycache__/multi_array.cpython-311.pyc,sha256=I9q9emRH-AgunGTzNZm5VpAnaXNdafr4h2vtZX-qMFw,14150
-DataVisual/__pycache__/tables.cpython-311.pyc,sha256=fE98mEzIUnOF7GEf29Y-u-ZD4_XIannULgDWwGdvsTk,1902
+DataVisual/VERSION,sha256=fQcrSFJrAjlQ5MSNsB6MJzVUpkARGfVpHnWJupvGXZ0,6
+DataVisual/__init__.py,sha256=clu51hpR4yR4P8T3TKgJ4HVmzKrEBXNNzRTCOvFDaB4,187
+DataVisual/multi_array.py,sha256=tSPdrnP9YaCDGqypjCbRWbZsfG60WRrZtuIgc7hT9UE,9689
+DataVisual/tables.py,sha256=mWCT2MInMWbp1QKZOMnpzLgxnFjAByf2qv4rX9hKcCI,844
+DataVisual/__pycache__/__init__.cpython-311.pyc,sha256=1RuMVi6f43FtT1MElU9CFvbGmLwUz4lNdAkmLHilWX4,312
+DataVisual/__pycache__/multi_array.cpython-311.pyc,sha256=XBxSBsSPM7R76rXYPv3xjDcQsaENMvBO2HNFk6vEv6I,14123
+DataVisual/__pycache__/tables.cpython-311.pyc,sha256=Sgzx2QOjVW3fXaDpzQuCBOVOOcLR0b4Uxe72B_qq17M,1866
 DataVisual/examples/README.rst,sha256=WB-wJy7MMO9ETk_nxJ-HmaekQlYJeQFWeZWpFBLIBa4,19
 DataVisual/tools/__init__.py,sha256=47DEQpj8HBSa-_TImW-5JCeuQeRkm5NMpJWZG3hSuFU,0
 DataVisual/tools/directories.py,sha256=7TZRNd4wEJ5l4XkpRuetBTFus4XpLcWFkDA8qVSY2lM,903
-DataVisual/units/__init__.py,sha256=PnNGndLMOLGh5HFUFRKGuAFuYaci45A2j-SmwGiAbiQ,51
-DataVisual/units/base_class.py,sha256=iKsJvunDtcxVuLvhJaCZKFA_Q2hqu2iWsPpUmYxCVAg,9470
+DataVisual/units/__init__.py,sha256=5UysA_MFJfQtqZvEl-8pFtDZTvG4x6wlPQaSfn6uCpw,143
+DataVisual/units/base_class.py,sha256=SIOXR1CcsQcqK4wqSoc6ANfo1F4RclmQ8YG7n1axDiQ,9489
 DataVisual/units/components.py,sha256=kAVGU7QdNH5S4BtOWW-2m9r1xK8apk5_JydC_t41OzQ,3460
-DataVisual/units/__pycache__/__init__.cpython-311.pyc,sha256=MWkQPXVDNYACnC8Hxl2DS5FdroRO-w6mRhlIXLimQ28,244
-DataVisual/units/__pycache__/base_class.cpython-311.pyc,sha256=KCFt3HpGzH8NNnmSPFrLKrff3ELxMZKs9A5OyHj3dW4,11371
-DataVisual/units/__pycache__/components.cpython-311.pyc,sha256=YRUrRaIjQg_ThgjuYGBEttJZsl5vbo7t7LrXA586iz0,7629
-DataVisual-1.4.0.dist-info/LICENSE,sha256=Ke_IyELN_sdt23XyXJ-cK1XuiqyNPaIKjHVkFCcy0uI,1073
-DataVisual-1.4.0.dist-info/METADATA,sha256=dr__kkI7kdeTtcHkJaCtbw56hxwXE3ag2b0YsNJhN70,3680
-DataVisual-1.4.0.dist-info/WHEEL,sha256=oiQVh_5PnQM0E3gPdiz09WCNmwiHDMaGer_elqB3coM,92
-DataVisual-1.4.0.dist-info/top_level.txt,sha256=noiHFlgpZk0PsyudveLPxwIAClGrpUFDpHoc_HiVXoI,11
-DataVisual-1.4.0.dist-info/RECORD,,
+DataVisual/units/__pycache__/__init__.cpython-311.pyc,sha256=32TDdqLA62uOoki2zucCAyKp_ognjn8hTpdS1CNqqUg,246
+DataVisual/units/__pycache__/base_class.cpython-311.pyc,sha256=RQJyHHbBPPIavS60wz8bKXlPvom-2R0UhPDeOrmZU5A,11444
+DataVisual/units/__pycache__/components.cpython-311.pyc,sha256=8oMt3PouklevtcjGVZTrxSHvqcNWcRBKsMz2m4RIDqo,7629
+DataVisual-1.4.1.dist-info/LICENSE,sha256=Ke_IyELN_sdt23XyXJ-cK1XuiqyNPaIKjHVkFCcy0uI,1073
+DataVisual-1.4.1.dist-info/METADATA,sha256=B3NUZ46GD7cHfIQmO5ToSHhBlNxWExmU0NeD5pkEG2k,3680
+DataVisual-1.4.1.dist-info/WHEEL,sha256=GJ7t_kWBFywbagK5eo9IoUwLW6oyOeTKmQ-9iHFVNxQ,92
+DataVisual-1.4.1.dist-info/top_level.txt,sha256=noiHFlgpZk0PsyudveLPxwIAClGrpUFDpHoc_HiVXoI,11
+DataVisual-1.4.1.dist-info/RECORD,,
```

